nuuly_bigquery_mcp_server/__init__.py
nuuly_bigquery_mcp_server/__main__.py
nuuly_bigquery_mcp_server/server.py
nuuly_bigquery_mcp_server-1.0.4.dist-info/METADATA
nuuly_bigquery_mcp_server-1.0.4.dist-info/WHEEL
nuuly_bigquery_mcp_server-1.0.4.dist-info/entry_points.txt
nuuly_bigquery_mcp_server-1.0.4.dist-info/top_level.txt
nuuly_bigquery_mcp_server-1.0.4.dist-info/RECORD
