Metadata-Version: 2.4
Name: nuuly-bigquery-mcp-server
Version: 1.0.4
Summary: MCP server for code editors, connects to Google BigQuery
Author-email: "URBN Inc." <engineering@nuuly.com>
License: Proprietary
Project-URL: Homepage, https://github.com/urbn/r15-mcp
Project-URL: Repository, https://github.com/urbn/r15-mcp
Requires-Python: >=3.8
Requires-Dist: fastmcp>=2.2.1
Requires-Dist: httpx>=0.24.0
Requires-Dist: fastapi>=0.95.0
Requires-Dist: uvicorn>=0.21.1
